Soundlib/__init__.py
Soundlib/_soundlib.pyd
dasoundlib-0.6.dist-info/METADATA
dasoundlib-0.6.dist-info/WHEEL
dasoundlib-0.6.dist-info/top_level.txt
dasoundlib-0.6.dist-info/RECORD
